{
  "$schema": "https://static.modelcontextprotocol.io/schemas/2025-12-11/server.schema.json",
  "name": "io.github.AynOps/AynOps",
  "description": "AynOps is a reconnaissance focused MCP Server which gives reconnaissance capabilities to AI Clients",
  "repository": {
    "url": "https://github.com/AynOps/AynOps",
    "source": "github"
  },
  "version": "1.1.2",
  "tags": ["cybersecurity", "reconnaissance", "whois", "dns", "nmap", "ssl", "cve", "security"],
  "packages": [
    {
      "registryType": "pypi",
      "identifier": "AynOps",
      "version": "1.1.2",
      "transport": {
        "type": "stdio"
      },
      "environmentVariables": [
        {
          "name": "ABUSEIPDB_API_KEY",
          "description": "Required for ip_reputation tool. Get free key at abuseipdb.com",
          "isRequired": false,
          "isSecret": true,
          "format": "string"
        }
      ]
    }
  ]
}